{"id": 9941730, "collectionNo": 240, "name": "Beast III/L", "originalName": "\u30d3\u30fc\u30b9\u30c8\u2162\uff0fL", "ruby": "\u30d3\u30fc\u30b9\u30c8\u2162\uff0fL", "battleName": "Kama/Mara", "originalBattleName": "\u30ab\u30fc\u30de\uff0f\u30de\u30fc\u30e9", "classId": 26, "className": "beastIIIL", "type": "enemyCollectionDetail", "flag": "normal", "flags": [], "rarity": 5, "cost": 16, "lvMax": 90, "extraAssets": {"charaGraph": {"ascension": {"0": "https://static.atlasacademy.io/JP/CharaGraph/9941730/9941730a.png"}}, "faces": {"ascension": {"0": "https://static.atlasacademy.io/JP/Faces/f_99417300.png"}}, "charaGraphEx": {}, "charaGraphName": {}, "narrowFigure": {}, "charaFigure": {"story": {"1098163700": "https://static.atlasacademy.io/JP/CharaFigure/1098163700/1098163700_merged.png", "1098163710": "https://static.atlasacademy.io/JP/CharaFigure/1098163710/1098163710_merged.png", "1098163720": "https://static.atlasacademy.io/JP/CharaFigure/1098163720/1098163720_merged.png"}}, "charaFigureForm": {}, "charaFigureMulti": {}, "charaFigureMultiCombine": {}, "charaFigureMultiLimitUp": {}, "commands": {}, "status": {}, "equipFace": {}, "image": {"story": {"0": "https://static.atlasacademy.io/JP/Image/back72600/back72600.png", "1": "https://static.atlasacademy.io/JP/Image/back72700/back72700.png", "2": "https://static.atlasacademy.io/JP/Image/back72705/back72705.png", "3": "https://static.atlasacademy.io/JP/Image/back72706/back72706.png", "4": "https://static.atlasacademy.io/JP/Image/back72707/back72707.png", "5": "https://static.atlasacademy.io/JP/Image/cut103_item01/cut103_item01.png", "6": "https://static.atlasacademy.io/JP/Image/cut103_item02/cut103_item02.png"}}, "spriteModel": {"ascension": {"0": "https://static.atlasacademy.io/JP/Servants/9941730/manifest.json", "1": "https://static.atlasacademy.io/JP/Servants/9941730/manifest.json", "2": "https://static.atlasacademy.io/JP/Servants/9941730/manifest.json", "3": "https://static.atlasacademy.io/JP/Servants/9941730/manifest.json", "4": "https://static.atlasacademy.io/JP/Servants/9941730/manifest.json"}}, "charaGraphChange": {}, "narrowFigureChange": {}, "facesChange": {}}, "gender": "female", "attribute": "beast", "traits": [{"id": 2, "name": "genderFemale"}, {"id": 118, "name": "classBeastIIIL"}, {"id": 204, "name": "attributeBeast"}, {"id": 301, "name": "alignmentChaotic"}, {"id": 304, "name": "alignmentEvil"}, {"id": 405, "name": "fiveStarServant"}, {"id": 2000, "name": "divine"}, {"id": 2001, "name": "humanoid"}, {"id": 2019, "name": "demonic"}, {"id": 2040, "name": "divineOrDemonOrUndead"}, {"id": 2113, "name": "king"}, {"id": 2835, "name": "immuneToPigify"}, {"id": 5000, "name": "canBeInBattle"}, {"id": 9941730, "name": "unknown"}], "starAbsorb": 100, "starGen": 102, "instantDeathChance": 0, "cards": ["quick", "quick", "arts", "buster", "buster"], "hitsDistribution": {"arts": [10, 20, 30, 40], "buster": [10, 20, 30, 40], "quick": [10, 20, 30, 40], "extra": [10, 20, 30, 40]}, "cardDetails": {"arts": {"hitsDistribution": [10, 20, 30, 40], "attackIndividuality": [{"id": 3002, "name": "attackMagical"}], "attackType": "one"}, "buster": {"hitsDistribution": [10, 20, 30, 40], "attackIndividuality": [{"id": 3002, "name": "attackMagical"}], "attackType": "one"}, "quick": {"hitsDistribution": [10, 20, 30, 40], "attackIndividuality": [{"id": 3002, "name": "attackMagical"}], "attackType": "one"}, "extra": {"hitsDistribution": [10, 20, 30, 40], "attackIndividuality": [{"id": 3002, "name": "attackMagical"}], "attackType": "one"}}, "atkBase": 2080, "atkMax": 13464, "hpBase": 2745, "hpMax": 18720, "relateQuestIds": [], "trialQuestIds": [], "growthCurve": 9999, "atkGrowth": [2080, 2193, 2307, 2421, 2535, 2649, 2763, 2876, 2990, 3104, 3229, 3343, 3457, 3571, 3685, 3798, 3912, 4026, 4140, 4254, 4379, 4493, 4607, 4721, 4834, 4948, 5062, 5176, 5290, 5404, 5529, 5643, 5757, 5870, 5984, 6098, 6212, 6326, 6440, 6553, 6679, 6792, 6906, 7020, 7134, 7248, 7362, 7476, 7589, 7703, 7828, 7942, 8056, 8170, 8284, 8398, 8511, 8625, 8739, 8853, 8978, 9092, 9206, 9320, 9434, 9547, 9661, 9775, 9889, 10003, 10128, 10242, 10356, 10470, 10583, 10697, 10811, 10925, 11039, 11153, 11278, 11392, 11505, 11619, 11733, 11847, 11961, 12075, 12188, 12302], "hpGrowth": [2745, 2904, 3064, 3224, 3384, 3543, 3703, 3863, 4023, 4182, 4358, 4518, 4677, 4837, 4997, 5157, 5316, 5476, 5636, 5796, 5971, 6131, 6291, 6451, 6610, 6770, 6930, 7090, 7249, 7409, 7585, 7745, 7904, 8064, 8224, 8384, 8543, 8703, 8863, 9023, 9198, 9358, 9518, 9678, 9837, 9997, 10157, 10317, 10476, 10636, 10812, 10972, 11131, 11291, 11451, 11611, 11770, 11930, 12090, 12250, 12425, 12585, 12745, 12905, 13064, 13224, 13384, 13544, 13703, 13863, 14039, 14199, 14358, 14518, 14678, 14838, 14997, 15157, 15317, 15477, 15652, 15812, 15972, 16132, 16291, 16451, 16611, 16771, 16930, 17090], "bondGrowth": [], "expGrowth": [0, 0, 0, 0, 0, 0, 0, 0, 0, 0, 0, 0, 0, 0, 0, 0, 0, 0, 0, 0, 0, 0, 0, 0, 0, 0, 0, 0, 0, 0, 0, 0, 0, 0, 0, 0, 0, 0, 0, 0, 0, 0, 0, 0, 0, 0, 0, 0, 0, 0, 0, 0, 0, 0, 0, 0, 0, 0, 0, 0, 0, 0, 0, 0, 0, 0, 0, 0, 0, 0, 0, 0, 0, 0, 0, 0, 0, 0, 0, 0, 0, 0, 0, 0, 0, 0, 0, 0, 0, 0], "expFeed": [10], "bondEquip": 0, "valentineEquip": [], "valentineScript": [], "limits": [{"limitCount": 0, "rarity": 5, "lvMax": 50, "hpBase": 2745, "hpMax": 18720, "atkBase": 2080, "atkMax": 13464, "criticalWeight": 100, "strength": "C", "endurance": "EX", "agility": "A", "magic": "EX", "luck": "B", "np": "EX", "deity": "B", "policy": "chaotic", "personality": "evil"}, {"limitCount": 1, "rarity": 5, "lvMax": 60, "hpBase": 2745, "hpMax": 18720, "atkBase": 2080, "atkMax": 13464, "criticalWeight": 100, "strength": "C", "endurance": "EX", "agility": "A", "magic": "EX", "luck": "B", "np": "EX", "deity": "B", "policy": "chaotic", "personality": "evil"}, {"limitCount": 2, "rarity": 5, "lvMax": 70, "hpBase": 2745, "hpMax": 18720, "atkBase": 2080, "atkMax": 13464, "criticalWeight": 100, "strength": "C", "endurance": "EX", "agility": "A", "magic": "EX", "luck": "B", "np": "EX", "deity": "B", "policy": "chaotic", "personality": "evil"}, {"limitCount": 3, "rarity": 5, "lvMax": 80, "hpBase": 2745, "hpMax": 18720, "atkBase": 2080, "atkMax": 13464, "criticalWeight": 100, "strength": "C", "endurance": "EX", "agility": "A", "magic": "EX", "luck": "B", "np": "EX", "deity": "B", "policy": "chaotic", "personality": "evil"}, {"limitCount": 4, "rarity": 5, "lvMax": 90, "hpBase": 2745, "hpMax": 18720, "atkBase": 2080, "atkMax": 13464, "criticalWeight": 100, "strength": "C", "endurance": "EX", "agility": "A", "magic": "EX", "luck": "B", "np": "EX", "deity": "B", "policy": "chaotic", "personality": "evil"}], "ascensionAdd": {"attribute": {"ascension": {}, "costume": {}}, "individuality": {"ascension": {"0": [], "1": [], "2": [], "3": [], "4": []}, "costume": {}}, "voicePrefix": {"ascension": {"0": 0, "1": 0, "2": 0, "3": 0, "4": 0}, "costume": {}}, "overWriteServantName": {"ascension": {}, "costume": {}}, "originalOverWriteServantName": {"ascension": {}, "costume": {}}, "overWriteServantBattleName": {"ascension": {}, "costume": {}}, "originalOverWriteServantBattleName": {"ascension": {}, "costume": {}}, "overWriteTDName": {"ascension": {}, "costume": {}}, "originalOverWriteTDName": {"ascension": {}, "costume": {}}, "overWriteTDRuby": {"ascension": {}, "costume": {}}, "overWriteTDFileName": {"ascension": {}, "costume": {}}, "overWriteTDRank": {"ascension": {}, "costume": {}}, "overWriteTDTypeText": {"ascension": {}, "costume": {}}, "lvMax": {"ascension": {"0": 50, "1": 60, "2": 70, "3": 80, "4": 90}, "costume": {}}, "rarity": {"ascension": {"0": 5, "1": 5, "2": 5, "3": 5, "4": 5}, "costume": {}}, "charaGraphChange": {"ascension": {}, "costume": {}}, "charaGraphChangeCommonRelease": {"ascension": {}, "costume": {}}, "faceChange": {"ascension": {}, "costume": {}}, "faceChangeCommonRelease": {"ascension": {}, "costume": {}}}, "traitAdd": [], "svtChange": [], "ascensionImage": [], "overwrites": [], "ascensionMaterials": {}, "skillMaterials": {}, "appendSkillMaterials": {}, "costumeMaterials": {}, "script": {}, "skills": [], "classPassive": [], "extraPassive": [], "appendPassive": [], "noblePhantasms": [{"id": 9941731, "num": 1, "npNum": 1, "card": "quick", "name": "Mara Avaruddha", "originalName": "\u611b\u306e\u4e16\u754c\u3001\u71c3\u3048\u308b\u5b87\u5b99", "ruby": "\u30de\u30fc\u30e9\u30fb\u30a2\u30f4\u30a1\u30ed\u30fc\u30c0", "icon": "https://static.atlasacademy.io/JP/Servants/Commands/9941730/card_servant_np.png", "rank": "EX", "type": "\u5bfe\u754c\u5b9d\u5177", "effectFlags": ["attackEnemyOne"], "detail": "\u81ea\u8eab\u306eQuick\u3001Arts\u3001Buster\u30ab\u30fc\u30c9\u6027\u80fd\u3092\u30a2\u30c3\u30d7(3\u30bf\u30fc\u30f3)<\u30aa\u30fc\u30d0\u30fc\u30c1\u30e3\u30fc\u30b8\u3067\u52b9\u679c\u30a2\u30c3\u30d7> \uff0b \u6575\u5358\u4f53\u306b\u8d85\u5f37\u529b\u306a\u653b\u6483\uff06\u9ad8\u78ba\u7387\u3067\u9b45\u4e86\u72b6\u614b\u3092\u4ed8\u4e0e(1\u30bf\u30fc\u30f3)", "unmodifiedDetail": "\u81ea\u8eab\u306eQuick\u3001Arts\u3001Buster\u30ab\u30fc\u30c9\u6027\u80fd\u3092\u30a2\u30c3\u30d7(3\u30bf\u30fc\u30f3)<\u30aa\u30fc\u30d0\u30fc\u30c1\u30e3\u30fc\u30b8\u3067\u52b9\u679c\u30a2\u30c3\u30d7> \uff0b \u6575\u5358\u4f53\u306b\u8d85\u5f37\u529b\u306a\u653b\u6483[{0}]\uff06\u9ad8\u78ba\u7387\u3067\u9b45\u4e86\u72b6\u614b\u3092\u4ed8\u4e0e(1\u30bf\u30fc\u30f3)", "npGain": {"buster": [58, 58, 58, 58, 58], "arts": [58, 58, 58, 58, 58], "quick": [58, 58, 58, 58, 58], "extra": [58, 58, 58, 58, 58], "defence": [300, 300, 300, 300, 300], "np": [58, 58, 58, 58, 58]}, "npDistribution": [1, 3, 5, 7, 9, 10, 12, 14, 16, 23], "svtId": 9941730, "strengthStatus": 0, "priority": 101, "condQuestId": 0, "condQuestPhase": 0, "releaseConditions": [], "individuality": [{"id": 3002, "name": "attackMagical"}, {"id": 4003, "name": "cardQuick"}, {"id": 4007, "name": "cardNP"}, {"id": 4102, "name": "stNP"}], "npSvts": [{"svtId": 9941730, "num": 1, "npNum": 1, "priority": 101, "damage": [1, 3, 5, 7, 9, 10, 12, 14, 16, 23], "strengthStatus": 0, "flag": 0, "imageIndex": 0, "condQuestId": 0, "condQuestPhase": 0, "condLv": 0, "condFriendshipRank": 0, "motion": 50, "card": "quick", "releaseConditions": []}], "script": {}, "functions": [{"funcId": 3576, "funcType": "addStateShort", "funcTargetType": "self", "funcTargetTeam": "playerAndEnemy", "funcPopupText": "\u30ab\u30fc\u30c9\u6027\u80fd\u30a2\u30c3\u30d7", "funcPopupIcon": "https://static.atlasacademy.io/JP/BuffIcons/bufficon_312.png", "functvals": [], "overWriteTvalsList": [], "funcquestTvals": [], "script": {}, "funcGroup": [], "buffs": [{"id": 1589, "name": "Card Effectiveness Up", "originalName": "\u30ab\u30fc\u30c9\u6027\u80fd\u30a2\u30c3\u30d7", "detail": "Quick\u3001Arts\u3001Buster\u30ab\u30fc\u30c9\u306e\u6027\u80fd\u3092\u30a2\u30c3\u30d7", "icon": "https://static.atlasacademy.io/JP/BuffIcons/bufficon_312.png", "type": "upCommandall", "buffGroup": 0, "script": {}, "originalScript": {}, "vals": [{"id": 3004, "name": "buffPositiveEffect"}, {"id": 3006, "name": "buffIncreaseDamage"}, {"id": 3094, "name": "quickBuff"}, {"id": 3092, "name": "artsBuff"}, {"id": 3093, "name": "busterBuff"}], "tvals": [{"id": 5000, "name": "canBeInBattle"}, {"id": 4003, "name": "cardQuick"}, {"id": 4001, "name": "cardArts"}, {"id": 4002, "name": "cardBuster"}], "ckSelfIndv": [{"id": 4003, "name": "cardQuick"}, {"id": 4001, "name": "cardArts"}, {"id": 4002, "name": "cardBuster"}], "ckOpIndv": [], "maxRate": 5000}], "svals": [{"Rate": 1000, "Turn": 3, "Count": -1, "Value": 200}, {"Rate": 1000, "Turn": 3, "Count": -1, "Value": 200}, {"Rate": 1000, "Turn": 3, "Count": -1, "Value": 200}, {"Rate": 1000, "Turn": 3, "Count": -1, "Value": 200}, {"Rate": 1000, "Turn": 3, "Count": -1, "Value": 200}], "svals2": [{"Rate": 1000, "Turn": 3, "Count": -1, "Value": 200}, {"Rate": 1000, "Turn": 3, "Count": -1, "Value": 200}, {"Rate": 1000, "Turn": 3, "Count": -1, "Value": 200}, {"Rate": 1000, "Turn": 3, "Count": -1, "Value": 200}, {"Rate": 1000, "Turn": 3, "Count": -1, "Value": 200}], "svals3": [{"Rate": 1000, "Turn": 3, "Count": -1, "Value": 200}, {"Rate": 1000, "Turn": 3, "Count": -1, "Value": 200}, {"Rate": 1000, "Turn": 3, "Count": -1, "Value": 200}, {"Rate": 1000, "Turn": 3, "Count": -1, "Value": 200}, {"Rate": 1000, "Turn": 3, "Count": -1, "Value": 200}], "svals4": [{"Rate": 1000, "Turn": 3, "Count": -1, "Value": 200}, {"Rate": 1000, "Turn": 3, "Count": -1, "Value": 200}, {"Rate": 1000, "Turn": 3, "Count": -1, "Value": 200}, {"Rate": 1000, "Turn": 3, "Count": -1, "Value": 200}, {"Rate": 1000, "Turn": 3, "Count": -1, "Value": 200}], "svals5": [{"Rate": 1000, "Turn": 3, "Count": -1, "Value": 200}, {"Rate": 1000, "Turn": 3, "Count": -1, "Value": 200}, {"Rate": 1000, "Turn": 3, "Count": -1, "Value": 200}, {"Rate": 1000, "Turn": 3, "Count": -1, "Value": 200}, {"Rate": 1000, "Turn": 3, "Count": -1, "Value": 200}]}, {"funcId": 12, "funcType": "damageNp", "funcTargetType": "enemy", "funcTargetTeam": "playerAndEnemy", "funcPopupText": "\u306a\u3057", "functvals": [], "overWriteTvalsList": [], "funcquestTvals": [], "script": {}, "funcGroup": [], "buffs": [], "svals": [{"Rate": 1000, "Value": 12000}, {"Rate": 1000, "Value": 14000}, {"Rate": 1000, "Value": 16000}, {"Rate": 1000, "Value": 18000}, {"Rate": 1000, "Value": 20000}], "svals2": [{"Rate": 1000, "Value": 12000}, {"Rate": 1000, "Value": 14000}, {"Rate": 1000, "Value": 16000}, {"Rate": 1000, "Value": 18000}, {"Rate": 1000, "Value": 20000}], "svals3": [{"Rate": 1000, "Value": 12000}, {"Rate": 1000, "Value": 14000}, {"Rate": 1000, "Value": 16000}, {"Rate": 1000, "Value": 18000}, {"Rate": 1000, "Value": 20000}], "svals4": [{"Rate": 1000, "Value": 12000}, {"Rate": 1000, "Value": 14000}, {"Rate": 1000, "Value": 16000}, {"Rate": 1000, "Value": 18000}, {"Rate": 1000, "Value": 20000}], "svals5": [{"Rate": 1000, "Value": 12000}, {"Rate": 1000, "Value": 14000}, {"Rate": 1000, "Value": 16000}, {"Rate": 1000, "Value": 18000}, {"Rate": 1000, "Value": 20000}]}, {"funcId": 2168, "funcType": "addState", "funcTargetType": "enemy", "funcTargetTeam": "playerAndEnemy", "funcPopupText": "\u9b45\u4e86", "funcPopupIcon": "https://static.atlasacademy.io/JP/BuffIcons/bufficon_502.png", "functvals": [], "overWriteTvalsList": [], "funcquestTvals": [], "script": {}, "funcGroup": [], "buffs": [{"id": 926, "name": "Charm", "originalName": "\u9b45\u4e86", "detail": "\u884c\u52d5\u4e0d\u80fd\u306b\u306a\u308b", "icon": "https://static.atlasacademy.io/JP/BuffIcons/bufficon_502.png", "type": "donotAct", "buffGroup": 501, "script": {}, "originalScript": {}, "vals": [{"id": 3005, "name": "buffNegativeEffect"}, {"id": 3010, "name": "buffMentalEffect"}, {"id": 3012, "name": "buffCharm"}, {"id": 2191, "name": "buffCharmFemale"}, {"id": 3045, "name": "buffImmobilize"}], "tvals": [], "ckSelfIndv": [], "ckOpIndv": [], "maxRate": 0}], "svals": [{"Rate": 5000, "Turn": 1, "Count": -1}, {"Rate": 5000, "Turn": 1, "Count": -1}, {"Rate": 5000, "Turn": 1, "Count": -1}, {"Rate": 5000, "Turn": 1, "Count": -1}, {"Rate": 5000, "Turn": 1, "Count": -1}], "svals2": [{"Rate": 5000, "Turn": 1, "Count": -1}, {"Rate": 5000, "Turn": 1, "Count": -1}, {"Rate": 5000, "Turn": 1, "Count": -1}, {"Rate": 5000, "Turn": 1, "Count": -1}, {"Rate": 5000, "Turn": 1, "Count": -1}], "svals3": [{"Rate": 5000, "Turn": 1, "Count": -1}, {"Rate": 5000, "Turn": 1, "Count": -1}, {"Rate": 5000, "Turn": 1, "Count": -1}, {"Rate": 5000, "Turn": 1, "Count": -1}, {"Rate": 5000, "Turn": 1, "Count": -1}], "svals4": [{"Rate": 5000, "Turn": 1, "Count": -1}, {"Rate": 5000, "Turn": 1, "Count": -1}, {"Rate": 5000, "Turn": 1, "Count": -1}, {"Rate": 5000, "Turn": 1, "Count": -1}, {"Rate": 5000, "Turn": 1, "Count": -1}], "svals5": [{"Rate": 5000, "Turn": 1, "Count": -1}, {"Rate": 5000, "Turn": 1, "Count": -1}, {"Rate": 5000, "Turn": 1, "Count": -1}, {"Rate": 5000, "Turn": 1, "Count": -1}, {"Rate": 5000, "Turn": 1, "Count": -1}]}]}]}